itranslator/__init__.py
itranslator/asyncio.py
itranslator/errors.py
itranslator/itranslator.py
itranslator-3.0.dist-info/LICENSE
itranslator-3.0.dist-info/METADATA
itranslator-3.0.dist-info/WHEEL
itranslator-3.0.dist-info/top_level.txt
itranslator-3.0.dist-info/RECORD
