Metadata-Version: 2.1
Name: itranslator
Version: 3.0
Summary: Text translation package based on Google Translate API 
Home-page: https://github.com/irvaniamirali/itranslator
Author: AmirAli Irvani
Author-email: social.irvaniamirali@gmail.com
Keywords: translate,translator,google,google-translate,free-translator,asyncio
Classifier: Programming Language :: Python :: 3.7
Classifier: Programming Language :: Python :: 3.8
Classifier: Programming Language :: Python :: 3.9
Classifier: Programming Language :: Python :: 3.10
Classifier: Programming Language :: Python :: 3.11
Classifier: Programming Language :: Python :: 3.12
Classifier: Topic :: Internet
Classifier: Topic :: Software Development :: Libraries
Classifier: Topic :: Software Development :: Libraries :: Python Modules
Requires-Python: ~=3.7
License-File: LICENSE
Requires-Dist: httpx
Requires-Dist: user-agent
